openmindat/__init__.py
openmindat/_countries.py
openmindat/_locgeoregion2.py
openmindat/_locobject.py
openmindat/_photo_count.py
openmindat/dana8.py
openmindat/geomaterials.py
openmindat/geomaterials_search.py
openmindat/localities.py
openmindat/localities_age.py
openmindat/localities_status.py
openmindat/localities_type.py
openmindat/mindat_api.py
openmindat/minerals_ima.py
openmindat/nickel_strunz.py
openmindat-0.1.3.dist-info/METADATA
openmindat-0.1.3.dist-info/WHEEL
openmindat-0.1.3.dist-info/licenses/LICENSE
openmindat-0.1.3.dist-info/RECORD
