Metadata-Version: 2.4
Name: openmindat
Version: 0.1.3
Summary: An alpha version for OpenMindat package
Author-email: Jiyin Zhang <jiyinz@uidaho.edu>
License: Apache-2.0
License-File: LICENSE
Keywords: api,data,mindat,mineral,openmindat,python
Classifier: Development Status :: 3 - Alpha
Classifier: License :: OSI Approved :: Apache Software License
Classifier: Programming Language :: Python :: 3
Classifier: Programming Language :: Python :: 3.10
Classifier: Topic :: Scientific/Engineering :: Information Analysis
Classifier: Topic :: Software Development :: Libraries :: Python Modules
Requires-Python: >=3.10
Requires-Dist: pyyaml
Requires-Dist: requests
Requires-Dist: tqdm
